dartpy.cpython-313-x86_64-linux-gnu.so
dartpy.libs/libGLU-ff1477cc.so.1.3.1
dartpy.libs/libOpenThreads-40f1b21a.so.3.3.1
dartpy.libs/libXi-9178a6bd.so.6.1.0
dartpy.libs/libXxf86vm-8446c95f.so.1.0.0
dartpy.libs/libassimp-6dbf32af.so.5.4.3
dartpy.libs/libccd-252352d2.so.2.0
dartpy.libs/libconsole_bridge-74a7293d.so.1.0
dartpy.libs/libfcl-e62f87aa.so.0.7.0
dartpy.libs/libglut-a761335e.so.3.10.0
dartpy.libs/liboctomap-f33cbde0.so.1.10.0
dartpy.libs/liboctomath-f45b7699.so.1.10.0
dartpy.libs/libosg-918cf1aa.so.3.7.0
dartpy.libs/libosgDB-d5a653a6.so.3.7.0
dartpy.libs/libosgGA-92a7c57e.so.3.7.0
dartpy.libs/libosgManipulator-f07690ad.so.3.7.0
dartpy.libs/libosgShadow-2d57b09e.so.3.7.0
dartpy.libs/libosgText-b23e4e3d.so.3.7.0
dartpy.libs/libosgUtil-5431abc7.so.3.7.0
dartpy.libs/libosgViewer-6e464f80.so.3.7.0
dartpy.libs/liburdfdom_model-c401d788.so.4.0
dartpy.libs/liburdfdom_model_state-9c22f9db.so.4.0
dartpy.libs/liburdfdom_sensor-ef1de772.so.4.0
dartpy.libs/liburdfdom_world-cc923b78.so.4.0
tests/__init__.py
tests/util.py
tests/integration/__init__.py
tests/integration/test_joint_force_torque.py
tests/unit/__init__.py
tests/unit/collision/__init__.py
tests/unit/collision/test_collision.py
tests/unit/common/__init__.py
tests/unit/common/test_logging.py
tests/unit/common/test_stopwatch.py
tests/unit/common/test_string.py
tests/unit/common/test_uri.py
tests/unit/constraint/__init__.py
tests/unit/constraint/test_constraint.py
tests/unit/dynamics/__init__.py
tests/unit/dynamics/test_aspect.py
tests/unit/dynamics/test_body_node.py
tests/unit/dynamics/test_inertia.py
tests/unit/dynamics/test_inverse_kinematics.py
tests/unit/dynamics/test_joint.py
tests/unit/dynamics/test_meta_skeleton.py
tests/unit/dynamics/test_simple_frame.py
tests/unit/dynamics/test_skeleton.py
tests/unit/math/__init__.py
tests/unit/math/test_random.py
tests/unit/optimizer/__init__.py
tests/unit/optimizer/test_optimizer.py
tests/unit/simulation/__init__.py
dartpy-6.16.6.dist-info/METADATA
dartpy-6.16.6.dist-info/WHEEL
dartpy-6.16.6.dist-info/top_level.txt
dartpy-6.16.6.dist-info/RECORD
dartpy-6.16.6.dist-info/licenses/LICENSE
dartpy-6.16.6.dist-info/sboms/auditwheel.cdx.json
