Metadata-Version: 2.4
Name: dartpy
Version: 6.16.6
Summary: Python API of Dynamic Animation and Robotics Toolkit.
Home-page: https://github.com/dartsim/dart.git
Author: Jeongseok Lee
Author-email: jslee02@gmail.com
License: BSD 2-Clause
Keywords: dartsim robotics
Classifier: Development Status :: 2 - Pre-Alpha
Classifier: Framework :: Robot Framework
Classifier: Intended Audience :: Science/Research
Classifier: License :: OSI Approved :: BSD License
Classifier: Topic :: Scientific/Engineering
Classifier: Operating System :: Microsoft :: Windows
Classifier: Operating System :: MacOS
Classifier: Operating System :: POSIX :: Linux
Requires-Python: >=3.7
License-File: LICENSE
Requires-Dist: numpy
Provides-Extra: test
Requires-Dist: pytest>=6.0; extra == "test"
Dynamic: author
Dynamic: author-email
Dynamic: classifier
Dynamic: description
Dynamic: description-content-type
Dynamic: home-page
Dynamic: keywords
Dynamic: license
Dynamic: license-file
Dynamic: provides-extra
Dynamic: requires-dist
Dynamic: requires-python
Dynamic: summary
